liquidz/lib/libliquidz_ffi.dylib
liquidz/core.py
liquidz/__init__.py
liquidz-0.6.0.dist-info/WHEEL
liquidz-0.6.0.dist-info/licenses/LICENSE
liquidz-0.6.0.dist-info/top_level.txt
liquidz-0.6.0.dist-info/METADATA
liquidz-0.6.0.dist-info/RECORD
