Metadata-Version: 2.4
Name: liquidz
Version: 0.6.0
Summary: High-performance Liquid template engine powered by Zig
Author-email: Pedro Pinera Buendia <pedro@ppinera.es>
License: MIT
Project-URL: Homepage, https://github.com/pepicrft/liquidz
Project-URL: Repository, https://github.com/pepicrft/liquidz
Project-URL: Issues, https://github.com/pepicrft/liquidz/issues
Keywords: liquid,template,templating,zig,fast,shopify
Classifier: Development Status :: 4 - Beta
Classifier: Intended Audience :: Developers
Classifier: License :: OSI Approved :: MIT License
Classifier: Programming Language :: Python :: 3
Classifier: Programming Language :: Python :: 3.8
Classifier: Programming Language :: Python :: 3.9
Classifier: Programming Language :: Python :: 3.10
Classifier: Programming Language :: Python :: 3.11
Classifier: Programming Language :: Python :: 3.12
Classifier: Topic :: Text Processing :: Markup
Requires-Python: >=3.8
License-File: LICENSE
Provides-Extra: dev
Requires-Dist: pytest>=7.0; extra == "dev"
Dynamic: license-file
